luminal_rs/__init__.py
luminal_rs-0.0.1.dist-info/LICENSE.txt
luminal_rs-0.0.1.dist-info/METADATA
luminal_rs-0.0.1.dist-info/WHEEL
luminal_rs-0.0.1.dist-info/top_level.txt
luminal_rs-0.0.1.dist-info/RECORD
