Metadata-Version: 2.1
Name: luminal-rs
Version: 0.0.1
Summary: Deep learning at the speed of light
Home-page: https://github.com/jafioti/luminal
Author: Joe Fioti
Author-email: jafioti@gmail.com
License: MIT
Platform: UNKNOWN
License-File: LICENSE.txt
